yaramod.cp311-win_amd64.pyd
yaramod/__init__.pyi
yaramod/py.typed
yaramod-4.6.0.dist-info/licenses/LICENSE
yaramod-4.6.0.dist-info/METADATA
yaramod-4.6.0.dist-info/WHEEL
yaramod-4.6.0.dist-info/top_level.txt
yaramod-4.6.0.dist-info/RECORD
